speedtune/__init__.py
speedtune/patch.py
speedtune-0.1.2.dist-info/licenses/LICENSE
speedtune-0.1.2.dist-info/METADATA
speedtune-0.1.2.dist-info/WHEEL
speedtune-0.1.2.dist-info/top_level.txt
speedtune-0.1.2.dist-info/RECORD
