Metadata-Version: 2.4
Name: speedtune
Version: 0.1.2
Summary: Thin wrappers around transformers to help speed up training/fine-tuning.
Author-email: Hari Shankar <shanh042.310@gmail.com>
License: MIT License
Classifier: Programming Language :: Python :: 3
Classifier: License :: OSI Approved :: MIT License
Classifier: Operating System :: OS Independent
License-File: LICENSE
Requires-Dist: torch>=2.0.0
Requires-Dist: transformers>=4.30.0
Requires-Dist: typing-extensions; python_version < "3.12"
Provides-Extra: test
Requires-Dist: pytest>=7.0; extra == "test"
Dynamic: license-file
